{
  "shelly": {
    "name": "2PM Plus Cover",
    "id": "shellyplus2pm-5443b23d81f8",
    "mac": "5443B23D81F8",
    "slot": 0,
    "model": "SNSW-102P16EU",
    "gen": 2,
    "fw_id": "20241011-114448/1.4.4-g6d2a586",
    "ver": "1.4.4",
    "app": "Plus2PM",
    "auth_en": false,
    "auth_domain": null,
    "profile": "cover"
  },
  "settings": {
    "ble": {
      "enable": false,
      "rpc": {
        "enable": true
      },
      "observer": {
        "enable": false
      }
    },
    "cloud": {
      "enable": true,
      "server": "shelly-103-eu.shelly.cloud:6022/jrpc"
    },
    "cover:0": {
      "id": 0,
      "name": "2PM Plus Cover",
      "motor": {
        "idle_power_thr": 2,
        "idle_confirm_period": 0.25
      },
      "maxtime_open": 20,
      "maxtime_close": 20,
      "initial_state": "stopped",
      "invert_directions": false,
      "in_mode": "dual",
      "swap_inputs": false,
      "safety_switch": {
        "enable": false,
        "direction": "both",
        "action": "stop",
        "allowed_move": null
      },
      "power_limit": 2800,
      "voltage_limit": 280,
      "undervoltage_limit": 0,
      "current_limit": 10,
      "obstruction_detection": {
        "enable": false,
        "direction": "both",
        "action": "stop",
        "power_thr": 5,
        "holdoff": 1
      }
    },
    "input:0": {
      "id": 0,
      "name": null,
      "type": "switch",
      "enable": true,
      "invert": false,
      "factory_reset": true
    },
    "input:1": {
      "id": 1,
      "name": null,
      "type": "switch",
      "enable": true,
      "invert": false,
      "factory_reset": true
    },
    "mqtt": {
      "enable": false,
      "server": null,
      "client_id": "shellyplus2pm-5443b23d81f8",
      "user": null,
      "ssl_ca": null,
      "topic_prefix": "shellyplus2pm-5443b23d81f8",
      "rpc_ntf": true,
      "status_ntf": false,
      "use_client_cert": false,
      "enable_rpc": true,
      "enable_control": true
    },
    "sys": {
      "device": {
        "name": "2PM Plus Cover",
        "mac": "5443B23D81F8",
        "fw_id": "20241011-114448/1.4.4-g6d2a586",
        "discoverable": true,
        "eco_mode": true,
        "profile": "cover",
        "addon_type": null
      },
      "location": null,
      "debug": {
        "level": 2,
        "file_level": null,
        "mqtt": {
          "enable": false
        },
        "websocket": {
          "enable": false
        },
        "udp": {
          "addr": null
        }
      },
      "ui_data": {
        "cover": "50"
      },
      "rpc_udp": {
        "dst_addr": null,
        "listen_port": null
      },
      "sntp": {
        "server": "time.google.com"
      },
      "cfg_rev": 51
    },
    "wifi": {
      "ap": {
        "ssid": "ShellyPlus2PM-5443B23D81F8",
        "is_open": true,
        "enable": false,
        "range_extender": {
          "enable": false
        }
      },
      "sta": {
        "ssid": "FibreBox_X6-12A4C7",
        "is_open": false,
        "enable": true,
        "ipv4mode": "dhcp",
        "ip": null,
        "netmask": null,
        "gw": null,
        "nameserver": null
      },
      "sta1": {
        "ssid": "wifiAlbatros",
        "is_open": false,
        "enable": true,
        "ipv4mode": "dhcp",
        "ip": null,
        "netmask": null,
        "gw": null,
        "nameserver": null
      },
      "roam": {
        "rssi_thr": -80,
        "interval": 60
      }
    },
    "ws": {
      "enable": false,
      "server": null,
      "ssl_ca": "ca.pem"
    }
  },
  "status": {
    "ble": {},
    "cloud": {
      "connected": true
    },
    "cover:0": {
      "id": 0,
      "source": "timeout",
      "state": "stopped",
      "apower": 0,
      "voltage": 236.5,
      "current": 0,
      "pf": 0,
      "freq": 50,
      "aenergy": {
        "total": 7.07,
        "by_minute": [0, 0, 0],
        "minute_ts": 1730475180
      },
      "temperature": {
        "tC": 40,
        "tF": 104
      },
      "pos_control": true,
      "last_direction": "close",
      "current_pos": 0
    },
    "input:0": {
      "id": 0,
      "state": false
    },
    "input:1": {
      "id": 1,
      "state": false
    },
    "mqtt": {
      "connected": false
    },
    "sys": {
      "mac": "5443B23D81F8",
      "restart_required": false,
      "time": "16:33",
      "unixtime": 1730475202,
      "uptime": 172507,
      "ram_size": 251984,
      "ram_free": 122496,
      "fs_size": 393216,
      "fs_free": 98304,
      "cfg_rev": 51,
      "kvs_rev": 0,
      "schedule_rev": 7,
      "webhook_rev": 5,
      "available_updates": {},
      "reset_reason": 1
    },
    "wifi": {
      "sta_ip": "192.168.1.218",
      "status": "got ip",
      "ssid": "FibreBox_X6-12A4C7",
      "rssi": -60
    },
    "ws": {
      "connected": false
    }
  },
  "components": [],
  "cfg_rev": 51,
  "offset": 0,
  "total": 0
}
