{
  "id": 0,
  "type": "response",
  "flags": 1024,
  "flag_qr": true,
  "opcode": "QUERY",
  "flag_aa": true,
  "flag_tc": false,
  "flag_rd": false,
  "flag_ra": false,
  "flag_z": false,
  "flag_ad": false,
  "flag_cd": false,
  "rcode": "NOERROR",
  "questions": [],
  "answers": [
    {
      "name": "_http._tcp.local",
      "type": "PTR",
      "ttl": 4500,
      "class": "IN",
      "flush": false,
      "data": "shellydimmer2-98CDAC0D01BB._http._tcp.local"
    },
    {
      "name": "shellydimmer2-98CDAC0D01BB._http._tcp.local",
      "type": "SRV",
      "ttl": 120,
      "class": "IN",
      "flush": true,
      "data": {
        "priority": 0,
        "weight": 0,
        "port": 80,
        "target": "shellydimmer2-98CDAC0D01BB.local"
      }
    },
    {
      "name": "shellydimmer2-98CDAC0D01BB._http._tcp.local",
      "type": "TXT",
      "ttl": 120,
      "class": "IN",
      "flush": true,
      "data": [
        "id=shellydimmer2-98CDAC0D01BB",
        "arch=esp8266",
        "app=dimmer-l51",
        "fw_version=1.0",
        "fw_id=20230913-114008/v1.14.0-gcb84623",
        "discoverable=false"
      ]
    },
    {
      "name": "_services._dns-sd._udp.local",
      "type": "PTR",
      "ttl": 4500,
      "class": "IN",
      "flush": false,
      "data": "_http._tcp.local"
    },
    {
      "name": "shellydimmer2-98CDAC0D01BB.local",
      "type": "A",
      "ttl": 120,
      "class": "IN",
      "flush": true,
      "data": "192.168.1.219"
    },
    {
      "name": "shellydimmer2-98CDAC0D01BB.local",
      "type": "NSEC",
      "ttl": 120,
      "class": "IN",
      "flush": true,
      "data": {
        "nextDomain": "shellydimmer2-98CDAC0D01BB.local",
        "rrtypes": [
          "A"
        ]
      }
    }
  ],
  "authorities": [],
  "additionals": []
}